ysoisochrone/__init__.py
ysoisochrone/bayesian.py
ysoisochrone/isochrone.py
ysoisochrone/plotting.py
ysoisochrone/utils.py
ysoisochrone-0.4.1b0.dist-info/LICENSE
ysoisochrone-0.4.1b0.dist-info/METADATA
ysoisochrone-0.4.1b0.dist-info/WHEEL
ysoisochrone-0.4.1b0.dist-info/top_level.txt
ysoisochrone-0.4.1b0.dist-info/RECORD
