Metadata-Version: 2.2
Name: ysoisochrone
Version: 0.4.1b0
Summary: Python package handles the young-stellar-objects isochrones, and one primary goal is to derive the stellar mass and ages from the isochrones.
Home-page: https://github.com/DingshanDeng/ysoisochrone
Author: Dingshan Deng
Author-email: Dingshan Deng <dingshandeng@arizona.edu>
Project-URL: Homepage, https://github.com/DingshanDeng/ysoisochrone
Project-URL: Issues, https://github.com/DingshanDeng/ysoisochrone/issues
Classifier: Programming Language :: Python :: 3
Classifier: Operating System :: OS Independent
Requires-Python: >=3.8
License-File: LICENSE
Requires-Dist: numpy
Requires-Dist: pandas
Requires-Dist: matplotlib>=3.3.4
Requires-Dist: scipy
Requires-Dist: requests
Requires-Dist: tqdm
Requires-Dist: jupyter
Requires-Dist: pytest
Dynamic: author
Dynamic: home-page
